dateinterval/__init__.py
dateinterval-0.1.dist-info/LICENSE
dateinterval-0.1.dist-info/METADATA
dateinterval-0.1.dist-info/WHEEL
dateinterval-0.1.dist-info/top_level.txt
dateinterval-0.1.dist-info/RECORD
