Metadata-Version: 2.1
Name: dateinterval
Version: 0.1
Summary: Summarize a list of dates with intervals
Home-page: https://github.com/AndreiTanasescu/dateinterval
Author: Andrei Tanasescu
Author-email: drdrei@protonmail.com
License: BSD 2
Platform: UNKNOWN
License-File: LICENSE
